imgsize-4.0.1.dist-info/METADATA
imgsize-4.0.1.dist-info/WHEEL
imgsize-4.0.1.dist-info/licenses/LICENSE
imgsize/__init__.py
imgsize/__init__.pyi
imgsize/imgsize.pypy310-pp73-aarch64-linux-gnu.so
imgsize/py.typed
imgsize-4.0.1.dist-info/RECORD
